easydownload/__init__.py
easydownload-0.0.4.dist-info/LICENSE
easydownload-0.0.4.dist-info/METADATA
easydownload-0.0.4.dist-info/WHEEL
easydownload-0.0.4.dist-info/top_level.txt
easydownload-0.0.4.dist-info/RECORD
