Metadata-Version: 2.1
Name: easydownload
Version: 0.0.4
Summary: make it easy to use requests to download
Home-page: https://gitee.com/ZeroSeeker/easydownload
Author: ZeroSeeker
Author-email: zeroseeker@foxmail.com
License: UNKNOWN
Platform: UNKNOWN
Classifier: Programming Language :: Python :: 3
Classifier: License :: OSI Approved :: MIT License
Classifier: Operating System :: OS Independent
License-File: LICENSE
Requires-Dist: requests (==2.27.1)
